pyfbx/__init__.py
pyfbx/__main__.py
pyfbx/api.py
pyfbx/client.py
pyfbx/fb.pem
pyfbx/mdns.py
pyfbx/utils.py
pyfbx/archive/__init__-239692e7-2f72-4d01-b35c-31ba152c79bf.py
pyfbx/archive/__main__-fab1502e-0721-4875-9bfa-ceeeb29d5162.py
pyfbx/archive/api-4fdb8d3f-a038-4ed0-b265-80d8c0ffae76.py
pyfbx/archive/client-d8b1a2b9-1a4b-46b1-897e-4617fb217738.py
pyfbx/archive/mdns-271ced2d-42d9-4d2d-882f-284df4640170.py
pyfbx/archive/mdns-d4798f16-3d44-423c-b963-4b6ac3467b75.py
pyfbx/archive/utils-7835d0bd-2b4a-489b-aa77-b7a4b621c45f.py
pyfbx/archive/utils-fccddd2b-4aa7-40c9-8a5e-88f9e0d53ea0.py
tests/__init__.py
tests/conftest.py
tests/conn_test.py
tests/sanity_test.py
pyfbx-0.0.8.dist-info/LICENSE
pyfbx-0.0.8.dist-info/METADATA
pyfbx-0.0.8.dist-info/WHEEL
pyfbx-0.0.8.dist-info/entry_points.txt
pyfbx-0.0.8.dist-info/top_level.txt
pyfbx-0.0.8.dist-info/RECORD
