Metadata-Version: 2.1
Name: pyfbx
Version: 0.0.8
Summary: Freebox thin client
Home-page: https://framagit.org/sun/pyfbx
Author-email: teebeenator@gmail.com
License: MIT
Platform: UNKNOWN
Classifier: Programming Language :: Python :: 3
Classifier: License :: OSI Approved :: MIT License
